mcp_file_downloader/__init__.py
mcp_file_downloader/server.py
mcp_file_downloader-0.1.2.dist-info/licenses/LICENSE
mcp_file_downloader-0.1.2.dist-info/METADATA
mcp_file_downloader-0.1.2.dist-info/WHEEL
mcp_file_downloader-0.1.2.dist-info/entry_points.txt
mcp_file_downloader-0.1.2.dist-info/top_level.txt
mcp_file_downloader-0.1.2.dist-info/RECORD
