Metadata-Version: 2.4
Name: mcp_file_downloader
Version: 0.1.2
Summary: MCP server to download a file from URL and save locally.
Home-page: https://github.com/yourusername/mcp_file_downloader
Author: evan
Author-email: you@example.com
License: MIT
Classifier: Programming Language :: Python :: 3
Classifier: License :: OSI Approved :: MIT License
Classifier: Operating System :: OS Independent
Requires-Python: >=3.8
License-File: LICENSE
Requires-Dist: fastmcp>=0.1.0
Requires-Dist: httpx>=0.24.0
Dynamic: license-file
